README.md
setup.cfg
setup.py
astute/__init__.py
astute.egg-info/PKG-INFO
astute.egg-info/SOURCES.txt
astute.egg-info/dependency_links.txt
astute.egg-info/top_level.txt